e3db/__init__.py
e3db/auth.py
e3db/base_crypto.py
e3db/client.py
e3db/config.py
e3db/exceptions.py
e3db/identity.py
e3db/nist_crypto.py
e3db/sodium_crypto.py
e3db/tsv1_auth.py
e3db/tests/__init__.py
e3db/tests/test_crypto.py
e3db/tests/test_identity.py
e3db/tests/test_integration.py
e3db/tests/test_notes.py
e3db/tests/test_search_integration.py
e3db/tests/test_share_integration.py
e3db/tests/test_tsv1_auth.py
e3db/types/__init__.py
e3db/types/authorizer_policy.py
e3db/types/client_details.py
e3db/types/client_info.py
e3db/types/encyption_key_pair.py
e3db/types/file.py
e3db/types/file_meta.py
e3db/types/incoming_sharing.py
e3db/types/key_pair.py
e3db/types/meta.py
e3db/types/note.py
e3db/types/note_keys.py
e3db/types/note_options.py
e3db/types/outgoing_sharing.py
e3db/types/query.py
e3db/types/query_result.py
e3db/types/record.py
e3db/types/search.py
e3db/types/search_params.py
e3db/types/search_range.py
e3db/types/search_result.py
e3db/types/signing_key_pair.py
e3db-2.3.0.dist-info/LICENSE.md
e3db-2.3.0.dist-info/METADATA
e3db-2.3.0.dist-info/WHEEL
e3db-2.3.0.dist-info/top_level.txt
e3db-2.3.0.dist-info/RECORD
