Metadata-Version: 2.1
Name: e3db
Version: 2.3.0
Summary: E3DB provides a familiar JSON-based NoSQL-style API for reading, writing, and querying end-to-end encrypted data in the cloud.
Home-page: https://github.com/tozny/e3db-python
Author: Tozny, LLC
Author-email: info@tozny.com
License: TOZNY NON-COMMERCIAL LICENSE
Download-URL: https://github.com/tozny/e3db-python/archive/2.3.0.tar.gz
Keywords: e3db,encryption,encrypted-store,tozstore
Platform: UNKNOWN
